mockingbirdforuse/__init__.py
mockingbirdforuse/encoder/__init__.py
mockingbirdforuse/encoder/audio.py
mockingbirdforuse/encoder/hparams.py
mockingbirdforuse/encoder/inference.py
mockingbirdforuse/encoder/model.py
mockingbirdforuse/log.py
mockingbirdforuse/synthesizer/__init__.py
mockingbirdforuse/synthesizer/gst_hyperparameters.py
mockingbirdforuse/synthesizer/hparams.py
mockingbirdforuse/synthesizer/inference.py
mockingbirdforuse/synthesizer/models/global_style_token.py
mockingbirdforuse/synthesizer/models/tacotron.py
mockingbirdforuse/synthesizer/utils/__init__.py
mockingbirdforuse/synthesizer/utils/cleaners.py
mockingbirdforuse/synthesizer/utils/logmmse.py
mockingbirdforuse/synthesizer/utils/numbers.py
mockingbirdforuse/synthesizer/utils/symbols.py
mockingbirdforuse/synthesizer/utils/text.py
mockingbirdforuse/vocoder/__init__.py
mockingbirdforuse/vocoder/distribution.py
mockingbirdforuse/vocoder/hifigan/__init__.py
mockingbirdforuse/vocoder/hifigan/hparams.py
mockingbirdforuse/vocoder/hifigan/inference.py
mockingbirdforuse/vocoder/hifigan/models.py
mockingbirdforuse/vocoder/wavernn/__init__.py
mockingbirdforuse/vocoder/wavernn/audio.py
mockingbirdforuse/vocoder/wavernn/hparams.py
mockingbirdforuse/vocoder/wavernn/inference.py
mockingbirdforuse/vocoder/wavernn/models/deepmind_version.py
mockingbirdforuse/vocoder/wavernn/models/fatchord_version.py
mockingbirdforuse-0.2.3.dist-info/LICENSE.txt
mockingbirdforuse-0.2.3.dist-info/WHEEL
mockingbirdforuse-0.2.3.dist-info/METADATA
mockingbirdforuse-0.2.3.dist-info/RECORD
