Metadata-Version: 2.1
Name: mockingbirdforuse
Version: 0.2.3
Summary: 
Author: meetwq
Author-email: meetwq@gmail.com
Requires-Python: >=3.8,<3.11
Classifier: Programming Language :: Python :: 3
Classifier: Programming Language :: Python :: 3.10
Classifier: Programming Language :: Python :: 3.8
Classifier: Programming Language :: Python :: 3.9
Requires-Dist: Unidecode (>=1.3.0,<2.0.0)
Requires-Dist: inflect (>=5.6.0,<6.0.0)
Requires-Dist: librosa (>=0.9.0,<0.10.0)
Requires-Dist: loguru (>=0.6.0,<0.7.0)
Requires-Dist: numba (>=0.55.0,<0.56.0)
Requires-Dist: numpy (>=1.21.0,<2.0.0)
Requires-Dist: pypinyin (>=0.40.0)
Requires-Dist: scipy (>=1.8.0,<2.0.0)
Requires-Dist: torch (>=1.10.0,<2.0.0)
Requires-Dist: webrtcvad (>=2.0.0,<3.0.0)
